bbible/__init__.py
bbible/data/kjv.json
bbible/data/nkjv.json
bbible-0.2.1.dist-info/licenses/LICENSE
bbible-0.2.1.dist-info/METADATA
bbible-0.2.1.dist-info/WHEEL
bbible-0.2.1.dist-info/top_level.txt
bbible-0.2.1.dist-info/RECORD
