Metadata-Version: 2.4
Name: bbible
Version: 0.2.1
Summary: Explore the Bible by verse or by meaning — with multi-version and AI topic search
Home-page: https://github.com/Biyi003/bbible
Author: Biyi Adebayo
Project-URL: Documentation, https://github.com/Biyi003/bbible#readme
Project-URL: Source, https://github.com/Biyi003/bbible
Project-URL: Bug Tracker, https://github.com/Biyi003/bbible/issues
Classifier: Programming Language :: Python :: 3
Classifier: License :: OSI Approved :: MIT License
Classifier: Operating System :: OS Independent
Classifier: Topic :: Religion
Requires-Python: >=3.6
License-File: LICENSE
Dynamic: author
Dynamic: classifier
Dynamic: description
Dynamic: description-content-type
Dynamic: home-page
Dynamic: license-file
Dynamic: project-url
Dynamic: requires-python
Dynamic: summary
